Metadata-Version: 2.1
Name: ke2-airflow-commons
Version: 0.1.0
Summary: Python package framework to work with Apache Airflow developed in KazanExpress Data Office
Author: Your Name
Author-email: you@example.com
Requires-Python: >=3.9,<4.0
Classifier: Programming Language :: Python :: 3
Classifier: Programming Language :: Python :: 3.9
Classifier: Programming Language :: Python :: 3.10
Classifier: Programming Language :: Python :: 3.11
Requires-Dist: SQLAlchemy (==1.4.46)
Requires-Dist: apache-airflow (==2.3.3)
Requires-Dist: apache-airflow-providers-amazon (==6.0.0)
Requires-Dist: apache-airflow-providers-cncf-kubernetes (>=4.4.0,<5.0.0)
Requires-Dist: apache-airflow-providers-postgres (==5.1.0)
Requires-Dist: apache-airflow-providers-telegram (>=3.0.0,<4.0.0)
Requires-Dist: clickhouse-driver (>=0.2.4,<0.3.0)
Requires-Dist: clickhouse-sqlalchemy (==0.2.3)
Requires-Dist: google-api-python-client (==2.76.0)
Requires-Dist: odd-models (>=2.0.8,<3.0.0)
Requires-Dist: pandas (>=1.5.0,<2.0.0)
Requires-Dist: pyarrow (>=9.0.0,<10.0.0)
Requires-Dist: s3fs (==2022.8.2)
